README.rst
setup.cfg
setup.py
wsgi_status/__init__.py
wsgi_status/monitor.py
wsgi_status.egg-info/PKG-INFO
wsgi_status.egg-info/SOURCES.txt
wsgi_status.egg-info/dependency_links.txt
wsgi_status.egg-info/requires.txt
wsgi_status.egg-info/top_level.txt