Metadata-Version: 1.0
Name: wsgi-status
Version: 0.2.3
Summary: Monitoring wsgi status as an upper wsgi middleware
Home-page: https://github.com/kizkoh/wsgi_status
Author: kizkoh
Author-email: mac-daisuki@live.com
License: MIT
Platform: UNKNOWN
